{
    "dataset": {
        "name": "coins",
        "label_name": "coin",
        "indices": null
    },
    "population": [
        {
            "sequence": "[[0, 0, 0, 0, 0], [28, 0, 0, 161, 31], [24, 0, 0, 147, 5], [21, 0, 1, 106, 173], [10, 1, 3, 241, 37], [14, 2, 1, 15, 251], [32, 4, 1, 255, 91], [8, 6, 2, 197, 71], [40, 1, 0, 107, 229], [30, 3, 6, 69, 249], [6, 1, 0, 173, 255], [4, 5, 1, 10, 79], [35, 5, 1, 6, 22], [25, 0, 10, 84, 144], [16, 5, 10, 0, 215], [38, 8, 3, 161, 110], [11, 3, 0, 108, 154], [26, 11, 3, 143, 201], [29, 5, 1, 39, 162], [35, 11, 15, 233, 147], [14, 12, 3, 35, 56], [15, 9, 7, 245, 202], [6, 15, 1, 20, 79], [16, 10, 17, 115, 200], [41, 21, 13, 7, 33], [41, 24, 16, 156, 84], [5, 3, 10, 224, 180], [5, 0, 15, 151, 137], [37, 24, 17, 66, 132], [22, 13, 0, 51, 250], [8, 18, 19, 27, 230], [0, 11, 0, 0, 0]]",
            "fitness": {
                "fitness": 0.15072074841032576,
                "time": 0.005928802490234375,
                "act_nodes": 4.0
            }
        },
        {
            "sequence": "[[0, 0, 0, 0, 0], [28, 0, 0, 161, 31], [3, 0, 0, 245, 5], [21, 0, 1, 106, 173], [10, 2, 3, 156, 37], [14, 2, 1, 15, 251], [32, 4, 1, 255, 92], [8, 2, 2, 197, 71], [40, 1, 0, 107, 229], [18, 3, 6, 69, 249], [6, 1, 4, 173, 255], [37, 4, 1, 10, 79], [35, 5, 1, 55, 22], [25, 0, 3, 84, 144], [16, 5, 10, 0, 215], [38, 8, 3, 161, 110], [11, 3, 0, 108, 39], [26, 11, 3, 143, 201], [29, 5, 1, 39, 162], [35, 11, 15, 233, 147], [14, 12, 0, 35, 56], [31, 9, 7, 245, 202], [6, 15, 21, 20, 79], [16, 6, 17, 115, 200], [41, 21, 13, 7, 33], [41, 24, 13, 156, 84], [5, 16, 10, 224, 180], [5, 0, 15, 151, 137], [37, 24, 27, 66, 132], [22, 13, 0, 51, 250], [8, 17, 19, 27, 119], [0, 11, 0, 0, 0]]",
            "fitness": {
                "fitness": 0.8,
                "time": 0.00021424293518066407,
                "act_nodes": 3.0
            }
        },
        {
            "sequence": "[[0, 0, 0, 0, 0], [41, 0, 0, 161, 31], [35, 1, 0, 147, 112], [21, 0, 1, 106, 173], [13, 3, 3, 180, 74], [15, 2, 4, 15, 243], [32, 4, 1, 255, 96], [27, 6, 2, 99, 71], [34, 1, 2, 36, 229], [4, 3, 1, 69, 249], [6, 2, 6, 173, 55], [3, 5, 1, 194, 41], [35, 5, 1, 13, 22], [35, 6, 10, 84, 144], [13, 5, 10, 176, 125], [38, 8, 3, 223, 110], [11, 9, 0, 108, 154], [32, 2, 3, 143, 238], [29, 0, 1, 168, 84], [35, 11, 13, 233, 3], [14, 12, 7, 115, 50], [7, 12, 0, 245, 165], [22, 15, 1, 20, 79], [7, 10, 0, 115, 220], [13, 21, 13, 254, 33], [41, 7, 20, 148, 84], [5, 3, 12, 34, 180], [5, 21, 15, 204, 118], [18, 24, 22, 148, 217], [18, 0, 8, 51, 34], [8, 18, 19, 27, 230], [0, 26, 0, 0, 0]]",
            "fitness": {
                "fitness": 0.8,
                "time": 0.00037832260131835936,
                "act_nodes": 2.0
            }
        },
        {
            "sequence": "[[0, 0, 0, 0, 0], [14, 0, 0, 161, 31], [24, 0, 0, 69, 5], [9, 0, 1, 106, 173], [10, 1, 3, 120, 178], [22, 3, 4, 15, 111], [21, 4, 5, 255, 91], [8, 5, 1, 197, 71], [40, 3, 0, 107, 229], [36, 0, 6, 186, 181], [37, 1, 3, 173, 255], [4, 5, 1, 243, 79], [35, 9, 1, 154, 22], [18, 2, 10, 15, 57], [16, 5, 7, 47, 55], [29, 8, 10, 161, 110], [11, 6, 0, 108, 154], [7, 11, 3, 143, 201], [29, 10, 1, 39, 162], [35, 11, 15, 233, 147], [14, 10, 13, 101, 113], [15, 9, 6, 245, 202], [25, 15, 1, 20, 6], [16, 10, 17, 16, 200], [41, 21, 17, 7, 33], [41, 22, 16, 156, 84], [21, 21, 10, 224, 60], [5, 24, 12, 151, 137], [37, 24, 4, 66, 132], [41, 13, 0, 51, 250], [8, 18, 19, 70, 243], [0, 11, 0, 0, 0]]",
            "fitness": {
                "fitness": 0.8,
                "time": 0.0008953094482421875,
                "act_nodes": 4.0
            }
        },
        {
            "sequence": "[[0, 0, 0, 0, 0], [28, 0, 0, 161, 159], [24, 0, 1, 147, 5], [21, 0, 2, 106, 173], [24, 1, 0, 241, 198], [14, 0, 1, 27, 79], [31, 4, 1, 255, 91], [8, 3, 2, 197, 71], [40, 7, 0, 107, 231], [30, 3, 6, 69, 249], [18, 1, 0, 45, 255], [6, 5, 1, 10, 79], [21, 10, 1, 6, 22], [10, 0, 10, 84, 25], [22, 7, 10, 176, 215], [8, 8, 3, 161, 71], [11, 4, 0, 122, 154], [26, 11, 3, 143, 201], [28, 9, 1, 39, 162], [40, 11, 14, 39, 49], [14, 12, 3, 35, 56], [15, 9, 16, 185, 202], [6, 15, 13, 20, 193], [3, 10, 17, 169, 202], [41, 21, 22, 7, 243], [41, 2, 16, 203, 169], [5, 1, 10, 21, 180], [5, 0, 19, 151, 97], [37, 24, 17, 66, 132], [22, 13, 27, 51, 250], [35, 14, 8, 185, 52], [0, 11, 0, 0, 0]]",
            "fitness": {
                "fitness": 0.8,
                "time": 0.0007008075714111328,
                "act_nodes": 3.0
            }
        },
        {
            "sequence": "[[0, 0, 0, 0, 0], [28, 0, 0, 132, 31], [24, 0, 0, 147, 5], [21, 1, 1, 106, 173], [10, 1, 3, 241, 37], [14, 2, 1, 236, 251], [32, 4, 1, 255, 91], [8, 6, 2, 197, 71], [40, 3, 0, 107, 229], [30, 3, 6, 69, 249], [6, 0, 0, 135, 255], [26, 5, 1, 10, 79], [35, 5, 1, 6, 22], [27, 10, 10, 84, 144], [16, 5, 10, 0, 215], [38, 8, 3, 161, 110], [37, 4, 0, 108, 127], [26, 11, 3, 143, 201], [29, 5, 1, 39, 162], [35, 11, 15, 233, 147], [14, 12, 3, 35, 61], [15, 9, 7, 245, 202], [6, 15, 15, 20, 79], [16, 10, 17, 115, 200], [41, 3, 13, 50, 84], [41, 24, 10, 156, 84], [34, 3, 10, 224, 180], [5, 0, 22, 151, 137], [37, 24, 17, 66, 132], [22, 13, 0, 51, 250], [8, 18, 19, 27, 230], [0, 11, 0, 0, 0]]",
            "fitness": {
                "fitness": 0.8,
                "time": 0.005626964569091797,
                "act_nodes": 3.0
            }
        }
    ],
    "decoding": {
        "metadata": {
            "rows": 1,
            "columns": 30,
            "n_in": 1,
            "n_out": 1,
            "n_para": 2,
            "n_conn": 2
        },
        "functions": [
            "max",
            "min",
            "mean",
            "add",
            "subtract",
            "bitwise_not",
            "bitwise_or",
            "bitwise_and",
            "bitwise_and_mask",
            "bitwise_xor",
            "sqrt",
            "pow2",
            "exp",
            "log",
            "median_blur",
            "gaussian_blur",
            "laplacian",
            "sobel",
            "robert_cross",
            "canny",
            "sharpen",
            "gabor",
            "abs_diff",
            "abs_diff2",
            "fluo_tophat",
            "rel_diff",
            "erode",
            "dilate",
            "open",
            "close",
            "morph_gradient",
            "morph_tophat",
            "morph_blackhat",
            "fill_holes",
            "remove_small_objects",
            "remove_small_holes",
            "threshold",
            "threshold_at_1",
            "distance_transform",
            "distance_transform_and_thresh",
            "inrange_bin",
            "inrange"
        ],
        "endpoint": {
            "name": "Fit Ellipse",
            "abbv": "ELPS",
            "arity": 1,
            "args": 0,
            "kwargs": {
                "min_axis": 20,
                "max_axis": 60
            }
        },
        "mode": "default"
    }
}