{
    "dataset": {
        "name": "coins",
        "label_name": "coin",
        "indices": null
    },
    "population": [
        {
            "sequence": "[[0, 0, 0, 0, 0], [40, 0, 0, 137, 228], [16, 1, 0, 201, 237], [23, 0, 2, 6, 152], [21, 3, 3, 124, 191], [13, 4, 2, 110, 221], [27, 1, 2, 234, 79], [14, 1, 5, 49, 134], [26, 3, 2, 32, 193], [12, 8, 1, 106, 50], [11, 0, 3, 255, 178], [33, 0, 6, 92, 115], [5, 4, 3, 192, 25], [32, 1, 10, 229, 187], [36, 7, 0, 65, 68], [8, 7, 14, 91, 230], [1, 1, 4, 135, 159], [23, 9, 6, 176, 53], [21, 8, 0, 87, 189], [17, 1, 0, 211, 173], [16, 6, 15, 58, 130], [22, 9, 12, 207, 38], [7, 19, 1, 144, 246], [35, 10, 2, 150, 59], [27, 21, 21, 81, 145], [1, 2, 6, 151, 9], [37, 7, 13, 217, 141], [18, 3, 7, 112, 170], [13, 26, 17, 123, 157], [27, 4, 26, 103, 68], [41, 18, 4, 135, 54], [0, 2, 0, 0, 0]]",
            "fitness": {
                "fitness": 0.05539017763768313,
                "time": 0.00042042732238769533,
                "act_nodes": 2.0
            }
        },
        {
            "sequence": "[[0, 0, 0, 0, 0], [28, 0, 0, 149, 112], [16, 1, 0, 121, 237], [16, 2, 2, 6, 152], [40, 1, 3, 124, 191], [11, 0, 3, 136, 30], [27, 1, 0, 63, 79], [31, 3, 1, 80, 134], [13, 7, 0, 251, 193], [11, 6, 6, 106, 50], [11, 0, 3, 99, 178], [33, 1, 7, 242, 83], [2, 4, 3, 192, 241], [25, 7, 7, 229, 187], [36, 7, 0, 65, 68], [35, 2, 1, 83, 230], [33, 1, 4, 135, 159], [23, 2, 2, 155, 95], [5, 8, 10, 34, 56], [36, 1, 6, 211, 7], [39, 8, 15, 205, 106], [22, 9, 17, 207, 46], [7, 8, 8, 24, 246], [35, 3, 21, 227, 6], [32, 16, 5, 205, 131], [6, 2, 3, 148, 49], [31, 21, 22, 44, 130], [33, 13, 6, 36, 38], [13, 26, 4, 123, 212], [27, 3, 19, 21, 126], [28, 18, 18, 137, 111], [0, 6, 0, 0, 0]]",
            "fitness": {
                "fitness": 0.8,
                "time": 0.0004626274108886719,
                "act_nodes": 2.0
            }
        },
        {
            "sequence": "[[0, 0, 0, 0, 0], [26, 0, 0, 137, 92], [16, 0, 0, 92, 132], [23, 1, 2, 6, 42], [21, 3, 3, 124, 111], [13, 1, 2, 110, 221], [27, 5, 2, 234, 132], [4, 1, 5, 211, 165], [9, 5, 1, 32, 193], [12, 8, 3, 214, 226], [41, 4, 3, 44, 178], [33, 4, 5, 92, 115], [11, 7, 1, 132, 218], [16, 0, 10, 138, 187], [36, 4, 0, 52, 68], [8, 7, 14, 91, 230], [1, 5, 0, 135, 159], [23, 8, 6, 176, 53], [16, 8, 8, 1, 189], [17, 1, 11, 211, 173], [16, 6, 15, 91, 130], [22, 18, 12, 207, 47], [7, 20, 19, 144, 246], [35, 7, 11, 150, 59], [26, 19, 5, 249, 3], [1, 21, 6, 213, 9], [37, 6, 13, 20, 229], [27, 10, 7, 244, 97], [13, 26, 17, 124, 157], [21, 1, 26, 201, 68], [41, 18, 5, 135, 73], [0, 2, 0, 0, 0]]",
            "fitness": {
                "fitness": 0.8,
                "time": 0.0002544403076171875,
                "act_nodes": 1.0
            }
        },
        {
            "sequence": "[[0, 0, 0, 0, 0], [35, 0, 0, 235, 228], [16, 0, 1, 201, 237], [2, 0, 1, 223, 152], [21, 1, 3, 124, 236], [13, 3, 2, 110, 221], [27, 0, 2, 147, 79], [14, 1, 6, 49, 134], [26, 7, 2, 139, 193], [39, 3, 2, 228, 47], [11, 0, 3, 17, 178], [33, 0, 6, 62, 115], [5, 4, 3, 192, 242], [32, 1, 2, 229, 187], [33, 7, 0, 29, 68], [8, 7, 14, 126, 230], [0, 15, 14, 135, 56], [22, 1, 15, 71, 165], [5, 8, 0, 87, 189], [26, 10, 12, 211, 173], [16, 0, 15, 58, 31], [8, 9, 19, 207, 114], [7, 13, 1, 144, 121], [35, 10, 2, 93, 137], [27, 21, 21, 81, 145], [4, 2, 6, 151, 9], [11, 7, 13, 217, 141], [4, 3, 18, 253, 155], [13, 26, 27, 123, 157], [27, 3, 26, 103, 68], [41, 20, 4, 135, 54], [0, 2, 0, 0, 0]]",
            "fitness": {
                "fitness": 0.8,
                "time": 0.0002495288848876953,
                "act_nodes": 1.0
            }
        },
        {
            "sequence": "[[0, 0, 0, 0, 0], [40, 0, 0, 112, 228], [25, 0, 1, 176, 108], [41, 0, 2, 54, 152], [30, 3, 3, 66, 139], [16, 3, 3, 110, 45], [37, 1, 1, 234, 79], [14, 6, 6, 49, 134], [27, 4, 3, 103, 81], [12, 6, 6, 112, 109], [11, 0, 3, 154, 44], [31, 0, 6, 92, 61], [23, 10, 7, 130, 136], [25, 2, 1, 169, 11], [36, 12, 12, 62, 147], [36, 5, 14, 35, 195], [1, 5, 3, 135, 159], [23, 9, 16, 146, 171], [21, 8, 2, 87, 85], [32, 14, 14, 211, 255], [18, 15, 3, 7, 112], [1, 16, 19, 207, 109], [7, 19, 6, 8, 136], [35, 5, 2, 150, 59], [39, 0, 21, 65, 142], [4, 2, 21, 151, 9], [37, 9, 9, 11, 117], [18, 22, 0, 112, 170], [6, 18, 25, 76, 157], [27, 4, 4, 103, 19], [38, 3, 4, 57, 54], [0, 11, 0, 0, 0]]",
            "fitness": {
                "fitness": 0.8,
                "time": 0.0004138469696044922,
                "act_nodes": 1.0
            }
        },
        {
            "sequence": "[[0, 0, 0, 0, 0], [40, 0, 0, 161, 228], [16, 1, 0, 120, 237], [23, 0, 2, 255, 152], [21, 3, 3, 124, 191], [21, 4, 4, 81, 221], [27, 0, 2, 234, 79], [9, 6, 5, 49, 134], [26, 3, 2, 187, 193], [25, 4, 1, 106, 144], [11, 0, 3, 255, 178], [33, 6, 6, 92, 107], [5, 4, 3, 192, 25], [32, 1, 10, 240, 187], [36, 7, 0, 98, 68], [8, 6, 6, 140, 163], [21, 1, 4, 135, 147], [23, 9, 6, 73, 53], [21, 8, 0, 241, 189], [17, 1, 0, 211, 173], [16, 8, 15, 58, 130], [22, 11, 12, 207, 183], [35, 19, 1, 144, 246], [35, 7, 2, 150, 59], [38, 18, 14, 81, 206], [1, 2, 6, 151, 9], [15, 7, 13, 236, 141], [18, 3, 7, 112, 170], [13, 26, 17, 123, 157], [3, 4, 26, 103, 218], [41, 18, 4, 135, 54], [0, 6, 0, 0, 0]]",
            "fitness": {
                "fitness": 0.8,
                "time": 0.0005556106567382813,
                "act_nodes": 1.0
            }
        }
    ],
    "decoding": {
        "metadata": {
            "rows": 1,
            "columns": 30,
            "n_in": 1,
            "n_out": 1,
            "n_para": 2,
            "n_conn": 2
        },
        "functions": [
            "max",
            "min",
            "mean",
            "add",
            "subtract",
            "bitwise_not",
            "bitwise_or",
            "bitwise_and",
            "bitwise_and_mask",
            "bitwise_xor",
            "sqrt",
            "pow2",
            "exp",
            "log",
            "median_blur",
            "gaussian_blur",
            "laplacian",
            "sobel",
            "robert_cross",
            "canny",
            "sharpen",
            "gabor",
            "abs_diff",
            "abs_diff2",
            "fluo_tophat",
            "rel_diff",
            "erode",
            "dilate",
            "open",
            "close",
            "morph_gradient",
            "morph_tophat",
            "morph_blackhat",
            "fill_holes",
            "remove_small_objects",
            "remove_small_holes",
            "threshold",
            "threshold_at_1",
            "distance_transform",
            "distance_transform_and_thresh",
            "inrange_bin",
            "inrange"
        ],
        "endpoint": {
            "name": "Fit Ellipse",
            "abbv": "ELPS",
            "arity": 1,
            "args": 0,
            "kwargs": {
                "min_axis": 20,
                "max_axis": 60
            }
        },
        "mode": "default"
    }
}