{
    "dataset": {
        "name": "coins",
        "label_name": "coin",
        "indices": null
    },
    "population": [
        {
            "sequence": "[[0, 0, 0, 0, 0], [27, 0, 0, 121, 119], [15, 0, 0, 60, 119], [27, 0, 1, 65, 241], [31, 3, 0, 198, 222], [3, 0, 4, 218, 141], [27, 4, 2, 210, 131], [28, 3, 6, 171, 241], [37, 3, 6, 152, 191], [13, 2, 2, 22, 201], [4, 1, 0, 7, 179], [37, 4, 0, 32, 17], [30, 7, 1, 43, 48], [41, 2, 4, 92, 199], [0, 9, 11, 234, 164], [3, 9, 3, 113, 13], [38, 15, 0, 126, 113], [5, 12, 9, 94, 230], [21, 4, 16, 82, 51], [6, 8, 0, 148, 136], [20, 15, 1, 129, 252], [23, 11, 3, 59, 190], [37, 0, 14, 55, 148], [6, 17, 21, 211, 10], [22, 10, 8, 103, 195], [24, 6, 11, 47, 72], [4, 5, 0, 6, 151], [18, 10, 13, 147, 95], [22, 12, 9, 113, 106], [1, 0, 25, 147, 223], [25, 15, 5, 193, 162], [0, 13, 0, 0, 0]]",
            "fitness": {
                "fitness": 0.14497774254647233,
                "time": 0.0005253791809082031,
                "act_nodes": 2.0
            }
        },
        {
            "sequence": "[[0, 0, 0, 0, 0], [27, 0, 0, 121, 239], [15, 0, 0, 60, 119], [27, 0, 1, 65, 241], [31, 3, 0, 198, 222], [3, 0, 4, 218, 141], [27, 0, 3, 6, 11], [12, 3, 6, 131, 172], [37, 3, 4, 152, 146], [15, 2, 2, 22, 201], [4, 1, 0, 95, 35], [37, 4, 9, 226, 17], [29, 7, 1, 43, 48], [41, 11, 4, 92, 44], [0, 9, 11, 234, 164], [3, 9, 3, 113, 13], [33, 3, 9, 88, 108], [5, 12, 6, 94, 167], [35, 1, 16, 82, 51], [6, 8, 0, 148, 136], [20, 6, 6, 5, 104], [13, 8, 3, 252, 125], [17, 0, 0, 166, 148], [6, 17, 21, 211, 10], [22, 14, 8, 247, 195], [24, 22, 13, 47, 190], [4, 5, 0, 6, 34], [18, 10, 13, 147, 52], [16, 12, 1, 113, 253], [1, 0, 25, 147, 199], [6, 15, 5, 110, 52], [0, 13, 0, 0, 0]]",
            "fitness": {
                "fitness": 0.8,
                "time": 0.0004767894744873047,
                "act_nodes": 4.0
            }
        },
        {
            "sequence": "[[0, 0, 0, 0, 0], [27, 0, 0, 22, 227], [15, 0, 0, 60, 119], [27, 0, 1, 65, 241], [31, 3, 0, 198, 222], [3, 0, 4, 218, 141], [27, 4, 2, 210, 131], [2, 3, 4, 171, 241], [39, 4, 6, 152, 191], [13, 2, 2, 22, 201], [26, 1, 0, 7, 179], [37, 10, 0, 32, 17], [30, 7, 1, 43, 0], [11, 2, 3, 92, 40], [22, 7, 11, 81, 28], [3, 2, 3, 113, 13], [21, 15, 12, 126, 208], [5, 12, 9, 66, 230], [21, 4, 2, 82, 157], [6, 13, 2, 72, 136], [20, 15, 1, 129, 252], [23, 11, 3, 59, 49], [37, 1, 14, 55, 148], [18, 17, 21, 211, 10], [22, 10, 8, 248, 13], [24, 6, 15, 47, 72], [4, 6, 0, 221, 151], [28, 3, 13, 216, 95], [22, 12, 9, 26, 106], [1, 0, 25, 147, 223], [22, 15, 16, 193, 162], [0, 27, 0, 0, 0]]",
            "fitness": {
                "fitness": 0.8,
                "time": 0.0006470203399658204,
                "act_nodes": 2.0
            }
        },
        {
            "sequence": "[[0, 0, 0, 0, 0], [27, 0, 0, 121, 119], [15, 1, 0, 60, 125], [27, 0, 1, 65, 241], [31, 3, 0, 198, 222], [3, 0, 4, 218, 141], [27, 4, 2, 210, 131], [28, 3, 4, 171, 241], [37, 3, 6, 152, 191], [7, 2, 2, 22, 201], [4, 3, 0, 7, 179], [37, 9, 0, 32, 17], [30, 7, 10, 43, 48], [41, 2, 4, 92, 29], [0, 9, 11, 234, 164], [3, 9, 5, 113, 13], [38, 15, 0, 155, 113], [5, 12, 9, 94, 230], [21, 4, 16, 82, 81], [15, 8, 0, 148, 136], [20, 15, 1, 192, 252], [23, 8, 3, 59, 190], [37, 0, 14, 220, 113], [6, 17, 21, 7, 10], [22, 10, 8, 103, 195], [24, 6, 11, 47, 221], [4, 5, 4, 236, 129], [18, 10, 17, 147, 95], [22, 12, 9, 113, 106], [1, 0, 25, 147, 223], [25, 15, 5, 193, 162], [0, 13, 0, 0, 0]]",
            "fitness": {
                "fitness": 0.7705783104267436,
                "time": 0.0006258487701416016,
                "act_nodes": 3.0
            }
        },
        {
            "sequence": "[[0, 0, 0, 0, 0], [27, 0, 0, 47, 152], [18, 0, 1, 60, 119], [27, 0, 1, 166, 241], [31, 3, 0, 198, 179], [3, 0, 4, 218, 141], [32, 4, 2, 210, 131], [28, 3, 1, 130, 7], [37, 3, 6, 99, 191], [13, 2, 2, 158, 201], [4, 7, 0, 7, 91], [37, 4, 0, 52, 17], [30, 0, 1, 252, 48], [41, 7, 4, 92, 199], [0, 9, 11, 35, 217], [9, 13, 3, 58, 13], [38, 15, 13, 83, 113], [5, 12, 3, 94, 230], [12, 4, 16, 82, 51], [20, 8, 0, 148, 136], [20, 15, 1, 129, 252], [23, 11, 3, 13, 190], [22, 0, 7, 55, 148], [6, 10, 1, 247, 10], [22, 10, 8, 103, 195], [22, 6, 12, 47, 72], [4, 5, 0, 6, 151], [18, 15, 13, 147, 95], [22, 0, 6, 113, 106], [1, 0, 25, 147, 223], [25, 15, 5, 193, 162], [0, 13, 0, 0, 0]]",
            "fitness": {
                "fitness": 0.783401317853781,
                "time": 0.000584268569946289,
                "act_nodes": 3.0
            }
        },
        {
            "sequence": "[[0, 0, 0, 0, 0], [27, 0, 0, 121, 85], [5, 1, 0, 60, 119], [27, 0, 1, 65, 231], [14, 3, 0, 198, 5], [33, 4, 2, 199, 141], [27, 0, 3, 36, 131], [28, 3, 0, 235, 217], [36, 6, 3, 45, 31], [15, 2, 2, 53, 131], [7, 1, 1, 20, 179], [37, 8, 0, 147, 17], [30, 7, 0, 71, 48], [41, 2, 4, 28, 199], [0, 6, 11, 111, 164], [3, 9, 3, 113, 13], [38, 15, 0, 126, 136], [13, 12, 9, 77, 230], [21, 12, 9, 82, 51], [6, 8, 12, 156, 136], [20, 15, 14, 129, 252], [23, 18, 3, 59, 190], [35, 0, 14, 219, 148], [24, 17, 21, 211, 10], [22, 10, 9, 103, 40], [24, 6, 11, 47, 72], [29, 5, 0, 6, 164], [18, 17, 13, 126, 95], [25, 15, 5, 58, 147], [1, 9, 24, 107, 5], [30, 1, 1, 61, 162], [0, 13, 0, 0, 0]]",
            "fitness": {
                "fitness": 0.8,
                "time": 0.0003600597381591797,
                "act_nodes": 3.0
            }
        }
    ],
    "decoding": {
        "metadata": {
            "rows": 1,
            "columns": 30,
            "n_in": 1,
            "n_out": 1,
            "n_para": 2,
            "n_conn": 2
        },
        "functions": [
            "max",
            "min",
            "mean",
            "add",
            "subtract",
            "bitwise_not",
            "bitwise_or",
            "bitwise_and",
            "bitwise_and_mask",
            "bitwise_xor",
            "sqrt",
            "pow2",
            "exp",
            "log",
            "median_blur",
            "gaussian_blur",
            "laplacian",
            "sobel",
            "robert_cross",
            "canny",
            "sharpen",
            "gabor",
            "abs_diff",
            "abs_diff2",
            "fluo_tophat",
            "rel_diff",
            "erode",
            "dilate",
            "open",
            "close",
            "morph_gradient",
            "morph_tophat",
            "morph_blackhat",
            "fill_holes",
            "remove_small_objects",
            "remove_small_holes",
            "threshold",
            "threshold_at_1",
            "distance_transform",
            "distance_transform_and_thresh",
            "inrange_bin",
            "inrange"
        ],
        "endpoint": {
            "name": "Fit Ellipse",
            "abbv": "ELPS",
            "arity": 1,
            "args": 0,
            "kwargs": {
                "min_axis": 20,
                "max_axis": 60
            }
        },
        "mode": "default"
    }
}