{
    "dataset": {
        "name": "coins",
        "label_name": "coin",
        "indices": null
    },
    "population": [
        {
            "sequence": "[[0, 0, 0, 0, 0], [20, 0, 0, 19, 116], [4, 1, 0, 34, 152], [24, 1, 2, 24, 185], [36, 1, 2, 88, 142], [30, 1, 3, 254, 165], [20, 3, 2, 238, 163], [12, 3, 3, 19, 219], [8, 5, 2, 110, 70], [34, 7, 7, 140, 20], [20, 7, 1, 188, 122], [36, 0, 5, 76, 22], [8, 9, 9, 88, 136], [31, 10, 10, 188, 115], [28, 8, 1, 83, 223], [3, 5, 11, 18, 106], [25, 3, 3, 1, 1], [17, 2, 9, 0, 156], [0, 6, 0, 130, 170], [13, 1, 4, 176, 51], [23, 12, 2, 209, 131], [15, 13, 3, 138, 18], [27, 13, 6, 77, 224], [13, 14, 22, 153, 78], [23, 1, 17, 229, 101], [31, 6, 19, 39, 103], [19, 5, 17, 11, 82], [40, 20, 15, 175, 231], [27, 21, 21, 80, 128], [38, 12, 11, 25, 37], [24, 10, 14, 25, 24], [0, 4, 0, 0, 0]]",
            "fitness": {
                "fitness": 0.07649902529419746,
                "time": 0.00043659210205078126,
                "act_nodes": 2.0
            }
        },
        {
            "sequence": "[[0, 0, 0, 0, 0], [14, 0, 0, 19, 131], [35, 0, 1, 173, 99], [24, 2, 2, 231, 43], [36, 1, 3, 88, 77], [0, 2, 3, 254, 165], [25, 3, 5, 158, 138], [27, 5, 3, 170, 247], [32, 5, 2, 103, 196], [34, 8, 7, 249, 20], [3, 7, 1, 188, 63], [32, 0, 10, 128, 22], [5, 0, 1, 41, 136], [5, 10, 11, 188, 252], [28, 13, 1, 141, 132], [8, 9, 4, 110, 240], [20, 14, 8, 56, 224], [26, 2, 9, 0, 156], [0, 6, 6, 15, 170], [10, 13, 3, 161, 51], [20, 12, 2, 112, 50], [3, 13, 16, 119, 188], [0, 7, 2, 77, 164], [13, 14, 22, 173, 151], [25, 16, 20, 229, 101], [31, 20, 19, 50, 64], [27, 0, 17, 173, 82], [17, 20, 15, 175, 37], [27, 21, 9, 79, 66], [39, 4, 11, 20, 27], [12, 21, 14, 128, 24], [0, 22, 0, 0, 0]]",
            "fitness": {
                "fitness": 0.8,
                "time": 0.008351993560791016,
                "act_nodes": 5.0
            }
        },
        {
            "sequence": "[[0, 0, 0, 0, 0], [20, 0, 0, 19, 116], [4, 1, 0, 34, 152], [24, 1, 2, 24, 185], [36, 1, 2, 1, 142], [30, 0, 3, 254, 165], [30, 3, 2, 238, 15], [12, 3, 3, 19, 219], [8, 1, 2, 110, 70], [34, 7, 7, 140, 20], [39, 7, 1, 188, 122], [11, 0, 5, 76, 22], [19, 9, 9, 88, 136], [31, 10, 10, 151, 115], [28, 8, 1, 83, 223], [11, 10, 11, 18, 106], [25, 0, 3, 1, 1], [17, 2, 9, 0, 53], [0, 6, 0, 130, 3], [13, 1, 4, 190, 51], [23, 12, 2, 209, 131], [15, 13, 3, 138, 18], [27, 13, 6, 77, 224], [13, 2, 22, 153, 78], [23, 1, 19, 42, 101], [31, 6, 19, 39, 103], [19, 5, 17, 11, 82], [40, 20, 15, 100, 231], [27, 10, 21, 80, 128], [38, 12, 11, 25, 184], [24, 10, 14, 25, 24], [0, 24, 0, 0, 0]]",
            "fitness": {
                "fitness": 0.8,
                "time": 0.00046677589416503905,
                "act_nodes": 3.0
            }
        },
        {
            "sequence": "[[0, 0, 0, 0, 0], [20, 0, 0, 19, 116], [4, 1, 0, 34, 152], [24, 0, 1, 250, 185], [36, 1, 2, 234, 142], [0, 2, 4, 254, 165], [20, 3, 2, 238, 163], [15, 4, 3, 186, 219], [8, 5, 2, 110, 70], [34, 7, 1, 140, 20], [20, 7, 6, 214, 122], [36, 0, 5, 198, 22], [8, 6, 9, 88, 51], [31, 10, 1, 199, 177], [28, 8, 1, 20, 247], [3, 9, 11, 33, 106], [25, 3, 3, 1, 112], [17, 2, 4, 0, 156], [0, 9, 0, 130, 185], [4, 1, 8, 176, 51], [23, 12, 2, 112, 131], [15, 13, 3, 138, 18], [27, 13, 6, 62, 84], [13, 14, 22, 48, 179], [23, 18, 17, 229, 101], [13, 6, 4, 39, 103], [19, 5, 17, 11, 171], [40, 20, 15, 175, 231], [27, 21, 21, 80, 128], [38, 12, 11, 25, 37], [24, 10, 14, 25, 24], [0, 7, 0, 0, 0]]",
            "fitness": {
                "fitness": 0.7658779931584949,
                "time": 0.0006254196166992187,
                "act_nodes": 3.0
            }
        },
        {
            "sequence": "[[0, 0, 0, 0, 0], [20, 0, 0, 19, 116], [4, 1, 0, 34, 145], [24, 1, 2, 24, 23], [36, 1, 2, 88, 142], [30, 1, 3, 254, 165], [37, 3, 2, 246, 163], [12, 3, 3, 19, 21], [8, 5, 1, 110, 70], [34, 7, 7, 140, 20], [20, 4, 1, 188, 122], [36, 7, 7, 76, 22], [9, 9, 9, 88, 136], [31, 10, 10, 188, 115], [28, 8, 1, 83, 223], [14, 5, 11, 18, 106], [25, 12, 3, 1, 1], [17, 2, 9, 0, 156], [0, 6, 0, 130, 170], [13, 1, 4, 176, 51], [23, 12, 2, 209, 180], [15, 13, 3, 138, 18], [27, 13, 6, 77, 224], [13, 14, 14, 153, 245], [23, 1, 17, 229, 101], [31, 6, 19, 39, 143], [19, 5, 17, 11, 82], [40, 20, 15, 180, 231], [27, 21, 10, 80, 128], [38, 12, 11, 25, 120], [24, 25, 14, 25, 24], [0, 5, 0, 0, 0]]",
            "fitness": {
                "fitness": 0.8,
                "time": 0.0002570152282714844,
                "act_nodes": 2.0
            }
        },
        {
            "sequence": "[[0, 0, 0, 0, 0], [20, 0, 0, 162, 116], [4, 1, 0, 226, 121], [24, 1, 2, 28, 185], [36, 1, 2, 65, 142], [30, 1, 1, 254, 165], [3, 3, 2, 51, 216], [32, 3, 5, 19, 92], [38, 5, 4, 110, 70], [22, 7, 7, 140, 241], [20, 3, 1, 188, 122], [2, 0, 6, 76, 22], [8, 9, 9, 88, 136], [24, 10, 10, 188, 115], [28, 8, 1, 83, 223], [39, 5, 11, 52, 247], [25, 3, 3, 90, 26], [17, 2, 9, 224, 228], [0, 10, 0, 41, 170], [13, 5, 2, 97, 51], [21, 12, 2, 209, 131], [15, 16, 0, 138, 18], [27, 13, 2, 151, 191], [13, 14, 14, 153, 86], [23, 1, 17, 229, 101], [31, 18, 19, 196, 103], [28, 5, 17, 23, 147], [40, 10, 10, 175, 231], [27, 21, 21, 80, 128], [38, 25, 11, 37, 22], [24, 6, 8, 25, 24], [0, 17, 0, 0, 0]]",
            "fitness": {
                "fitness": 0.8,
                "time": 0.0003578662872314453,
                "act_nodes": 3.0
            }
        }
    ],
    "decoding": {
        "metadata": {
            "rows": 1,
            "columns": 30,
            "n_in": 1,
            "n_out": 1,
            "n_para": 2,
            "n_conn": 2
        },
        "functions": [
            "max",
            "min",
            "mean",
            "add",
            "subtract",
            "bitwise_not",
            "bitwise_or",
            "bitwise_and",
            "bitwise_and_mask",
            "bitwise_xor",
            "sqrt",
            "pow2",
            "exp",
            "log",
            "median_blur",
            "gaussian_blur",
            "laplacian",
            "sobel",
            "robert_cross",
            "canny",
            "sharpen",
            "gabor",
            "abs_diff",
            "abs_diff2",
            "fluo_tophat",
            "rel_diff",
            "erode",
            "dilate",
            "open",
            "close",
            "morph_gradient",
            "morph_tophat",
            "morph_blackhat",
            "fill_holes",
            "remove_small_objects",
            "remove_small_holes",
            "threshold",
            "threshold_at_1",
            "distance_transform",
            "distance_transform_and_thresh",
            "inrange_bin",
            "inrange"
        ],
        "endpoint": {
            "name": "Fit Ellipse",
            "abbv": "ELPS",
            "arity": 1,
            "args": 0,
            "kwargs": {
                "min_axis": 20,
                "max_axis": 60
            }
        },
        "mode": "default"
    }
}