{
    "dataset": {
        "name": "coins",
        "label_name": "coin",
        "indices": null
    },
    "population": [
        {
            "sequence": "[[0, 0, 0, 0, 0], [31, 0, 0, 25, 7], [41, 1, 1, 84, 34], [10, 1, 2, 233, 95], [29, 0, 2, 9, 185], [3, 4, 3, 240, 198], [1, 0, 4, 94, 59], [23, 6, 5, 82, 226], [2, 4, 0, 235, 62], [41, 2, 1, 234, 246], [40, 8, 1, 244, 114], [5, 5, 3, 86, 159], [10, 1, 4, 145, 242], [27, 4, 12, 60, 89], [33, 10, 6, 20, 124], [22, 13, 8, 43, 115], [19, 6, 6, 105, 235], [2, 13, 14, 181, 107], [38, 8, 12, 219, 205], [15, 16, 4, 168, 229], [40, 4, 0, 114, 212], [30, 8, 16, 18, 150], [27, 14, 15, 186, 177], [33, 14, 12, 156, 171], [30, 20, 22, 37, 16], [9, 11, 7, 244, 243], [5, 23, 4, 231, 62], [23, 6, 13, 164, 213], [7, 4, 16, 129, 194], [27, 5, 6, 48, 20], [6, 8, 6, 64, 10], [0, 23, 0, 0, 0]]",
            "fitness": {
                "fitness": 0.04932592209865634,
                "time": 0.000851583480834961,
                "act_nodes": 5.0
            }
        },
        {
            "sequence": "[[0, 0, 0, 0, 0], [31, 0, 0, 25, 7], [41, 0, 1, 84, 34], [10, 1, 2, 233, 14], [29, 0, 2, 9, 185], [3, 4, 3, 240, 198], [1, 0, 4, 94, 59], [33, 6, 5, 82, 226], [2, 4, 0, 235, 62], [41, 2, 8, 234, 246], [40, 8, 1, 43, 114], [5, 5, 3, 86, 159], [10, 1, 4, 170, 242], [27, 4, 12, 60, 89], [33, 10, 6, 20, 124], [22, 13, 8, 43, 115], [19, 6, 6, 105, 110], [2, 13, 14, 181, 191], [38, 8, 12, 219, 205], [15, 16, 4, 168, 229], [25, 4, 0, 114, 212], [30, 11, 10, 18, 17], [27, 14, 15, 186, 177], [33, 14, 9, 156, 171], [30, 20, 18, 37, 16], [9, 11, 7, 125, 243], [5, 5, 4, 231, 62], [23, 6, 13, 164, 213], [37, 4, 16, 129, 226], [17, 5, 6, 116, 20], [6, 8, 6, 64, 10], [0, 28, 0, 0, 0]]",
            "fitness": {
                "fitness": 0.8,
                "time": 0.0002463340759277344,
                "act_nodes": 2.0
            }
        },
        {
            "sequence": "[[0, 0, 0, 0, 0], [31, 0, 0, 194, 7], [41, 1, 1, 84, 237], [35, 1, 2, 234, 95], [29, 0, 2, 9, 185], [3, 1, 1, 240, 198], [1, 0, 4, 94, 59], [23, 6, 5, 82, 226], [2, 6, 0, 235, 62], [41, 2, 7, 234, 246], [40, 8, 1, 101, 114], [5, 2, 3, 86, 159], [10, 1, 4, 145, 242], [27, 4, 12, 60, 163], [33, 10, 6, 20, 124], [22, 13, 8, 43, 115], [37, 6, 6, 105, 235], [2, 13, 14, 181, 107], [38, 8, 12, 219, 205], [38, 16, 4, 168, 229], [40, 4, 0, 114, 212], [30, 8, 16, 56, 150], [3, 14, 15, 186, 112], [38, 14, 12, 156, 97], [30, 20, 22, 37, 16], [9, 11, 7, 244, 243], [5, 23, 23, 231, 62], [23, 6, 13, 214, 213], [7, 4, 16, 129, 194], [27, 5, 6, 48, 20], [6, 8, 6, 64, 10], [0, 23, 0, 0, 0]]",
            "fitness": {
                "fitness": 0.8,
                "time": 0.0009891033172607423,
                "act_nodes": 6.0
            }
        },
        {
            "sequence": "[[0, 0, 0, 0, 0], [31, 0, 0, 5, 7], [41, 1, 1, 84, 34], [10, 1, 2, 233, 95], [29, 0, 2, 9, 185], [3, 4, 3, 240, 198], [1, 0, 4, 94, 59], [23, 3, 3, 82, 196], [2, 5, 0, 235, 62], [41, 2, 1, 234, 246], [40, 8, 1, 244, 156], [5, 5, 3, 86, 159], [10, 1, 4, 145, 242], [27, 4, 12, 60, 110], [33, 10, 6, 20, 124], [22, 13, 8, 43, 115], [10, 6, 8, 105, 235], [2, 13, 14, 181, 107], [38, 8, 12, 219, 205], [15, 16, 4, 168, 229], [40, 4, 0, 114, 212], [30, 8, 16, 18, 150], [27, 14, 15, 186, 150], [33, 21, 12, 156, 171], [30, 20, 22, 22, 16], [9, 11, 7, 211, 78], [5, 23, 4, 231, 62], [23, 6, 13, 164, 213], [7, 13, 16, 129, 154], [27, 5, 6, 86, 20], [6, 8, 6, 64, 10], [0, 23, 0, 0, 0]]",
            "fitness": {
                "fitness": 0.8,
                "time": 0.0006196022033691407,
                "act_nodes": 7.0
            }
        },
        {
            "sequence": "[[0, 0, 0, 0, 0], [31, 0, 0, 25, 64], [41, 1, 1, 84, 34], [10, 1, 0, 233, 95], [29, 0, 2, 9, 185], [3, 4, 3, 240, 198], [1, 0, 4, 217, 59], [23, 1, 5, 82, 226], [2, 4, 4, 235, 62], [41, 2, 1, 234, 246], [40, 8, 1, 235, 114], [5, 5, 1, 86, 159], [10, 1, 4, 145, 242], [27, 4, 12, 60, 85], [33, 10, 6, 20, 200], [22, 11, 8, 43, 115], [19, 6, 12, 105, 235], [2, 13, 14, 181, 173], [38, 8, 2, 219, 205], [15, 16, 4, 168, 229], [40, 4, 0, 114, 7], [30, 8, 16, 18, 150], [27, 14, 15, 186, 177], [33, 11, 12, 156, 171], [30, 20, 1, 37, 16], [9, 11, 7, 244, 243], [5, 23, 4, 231, 62], [12, 6, 13, 164, 92], [7, 8, 16, 54, 194], [27, 5, 6, 48, 20], [6, 8, 1, 64, 10], [0, 23, 0, 0, 0]]",
            "fitness": {
                "fitness": 0.8,
                "time": 0.0008357524871826172,
                "act_nodes": 6.0
            }
        },
        {
            "sequence": "[[0, 0, 0, 0, 0], [31, 0, 0, 25, 7], [41, 1, 1, 23, 34], [10, 2, 2, 233, 95], [29, 0, 2, 9, 185], [3, 4, 3, 240, 198], [2, 0, 4, 94, 59], [41, 0, 5, 82, 226], [2, 4, 0, 235, 62], [7, 2, 1, 234, 246], [39, 8, 1, 244, 114], [12, 5, 3, 86, 159], [10, 1, 4, 108, 242], [27, 4, 12, 60, 89], [33, 10, 6, 20, 124], [22, 13, 8, 43, 115], [19, 6, 6, 105, 235], [2, 7, 14, 181, 107], [38, 8, 12, 219, 205], [31, 16, 4, 192, 229], [40, 4, 13, 114, 212], [30, 8, 20, 18, 150], [27, 14, 15, 38, 177], [33, 14, 12, 156, 171], [30, 20, 22, 37, 16], [9, 6, 7, 150, 177], [5, 23, 4, 231, 62], [23, 6, 21, 164, 213], [7, 21, 16, 205, 194], [27, 5, 6, 48, 20], [6, 8, 6, 64, 106], [0, 19, 0, 0, 0]]",
            "fitness": {
                "fitness": 0.054007101983320815,
                "time": 0.0013752460479736328,
                "act_nodes": 4.0
            }
        }
    ],
    "decoding": {
        "metadata": {
            "rows": 1,
            "columns": 30,
            "n_in": 1,
            "n_out": 1,
            "n_para": 2,
            "n_conn": 2
        },
        "functions": [
            "max",
            "min",
            "mean",
            "add",
            "subtract",
            "bitwise_not",
            "bitwise_or",
            "bitwise_and",
            "bitwise_and_mask",
            "bitwise_xor",
            "sqrt",
            "pow2",
            "exp",
            "log",
            "median_blur",
            "gaussian_blur",
            "laplacian",
            "sobel",
            "robert_cross",
            "canny",
            "sharpen",
            "gabor",
            "abs_diff",
            "abs_diff2",
            "fluo_tophat",
            "rel_diff",
            "erode",
            "dilate",
            "open",
            "close",
            "morph_gradient",
            "morph_tophat",
            "morph_blackhat",
            "fill_holes",
            "remove_small_objects",
            "remove_small_holes",
            "threshold",
            "threshold_at_1",
            "distance_transform",
            "distance_transform_and_thresh",
            "inrange_bin",
            "inrange"
        ],
        "endpoint": {
            "name": "Fit Ellipse",
            "abbv": "ELPS",
            "arity": 1,
            "args": 0,
            "kwargs": {
                "min_axis": 20,
                "max_axis": 60
            }
        },
        "mode": "default"
    }
}