{
    "dataset": {
        "name": "coins",
        "label_name": "coin",
        "indices": null
    },
    "population": [
        {
            "sequence": "[[0, 0, 0, 0, 0], [3, 0, 0, 37, 102], [10, 0, 0, 35, 159], [24, 2, 0, 194, 8], [40, 2, 0, 112, 106], [14, 3, 2, 34, 30], [25, 1, 4, 192, 58], [31, 2, 6, 112, 87], [6, 0, 2, 136, 112], [23, 3, 4, 193, 75], [31, 0, 5, 14, 103], [28, 5, 5, 146, 101], [1, 4, 1, 94, 178], [16, 1, 2, 152, 244], [20, 1, 7, 17, 130], [12, 5, 5, 113, 240], [9, 13, 4, 231, 208], [35, 12, 16, 198, 117], [36, 2, 3, 1, 50], [19, 11, 13, 166, 221], [34, 18, 10, 181, 183], [31, 2, 3, 88, 45], [31, 1, 21, 202, 48], [11, 21, 0, 4, 24], [19, 20, 11, 220, 83], [35, 1, 21, 172, 58], [4, 9, 18, 215, 198], [30, 24, 21, 147, 242], [33, 10, 15, 184, 167], [2, 16, 28, 63, 199], [27, 10, 19, 199, 36], [0, 19, 0, 0, 0]]",
            "fitness": {
                "fitness": 0.03179771116700523,
                "time": 0.010368251800537109,
                "act_nodes": 5.0
            }
        },
        {
            "sequence": "[[0, 0, 0, 0, 0], [19, 0, 0, 37, 102], [25, 1, 0, 35, 159], [24, 2, 0, 194, 125], [40, 2, 0, 112, 106], [14, 3, 4, 34, 30], [19, 1, 4, 192, 58], [31, 2, 6, 112, 87], [6, 0, 2, 136, 112], [12, 3, 4, 240, 75], [31, 0, 5, 182, 83], [28, 5, 5, 146, 246], [1, 4, 1, 94, 178], [16, 5, 2, 152, 244], [20, 1, 7, 17, 130], [35, 5, 5, 113, 240], [9, 13, 4, 231, 208], [25, 12, 16, 198, 117], [36, 10, 3, 1, 50], [19, 11, 13, 166, 67], [34, 18, 10, 181, 183], [31, 2, 3, 88, 45], [31, 1, 21, 202, 48], [11, 21, 0, 4, 24], [19, 20, 13, 220, 83], [35, 1, 17, 172, 58], [4, 9, 18, 215, 198], [30, 24, 21, 147, 242], [33, 10, 15, 184, 167], [2, 16, 28, 63, 236], [27, 5, 19, 240, 36], [0, 19, 0, 0, 0]]",
            "fitness": {
                "fitness": 0.8,
                "time": 0.010925817489624023,
                "act_nodes": 6.0
            }
        },
        {
            "sequence": "[[0, 0, 0, 0, 0], [6, 0, 0, 37, 102], [10, 0, 0, 35, 159], [24, 2, 0, 194, 8], [40, 2, 0, 112, 106], [14, 3, 2, 34, 30], [16, 1, 4, 192, 58], [31, 2, 6, 112, 87], [6, 0, 2, 136, 112], [23, 3, 4, 193, 191], [5, 0, 1, 14, 103], [5, 1, 2, 101, 101], [1, 4, 1, 94, 178], [16, 1, 2, 152, 244], [20, 1, 7, 216, 130], [12, 5, 5, 113, 240], [9, 13, 4, 231, 208], [35, 12, 16, 198, 117], [39, 5, 3, 1, 50], [19, 11, 13, 166, 221], [34, 18, 11, 181, 183], [31, 2, 15, 88, 45], [31, 1, 4, 202, 48], [11, 16, 0, 4, 24], [19, 19, 20, 220, 171], [35, 1, 21, 172, 58], [4, 9, 18, 215, 198], [30, 2, 21, 147, 242], [33, 10, 15, 184, 167], [2, 16, 28, 63, 199], [27, 10, 19, 199, 192], [0, 19, 0, 0, 0]]",
            "fitness": {
                "fitness": 0.04301674380965759,
                "time": 0.001267385482788086,
                "act_nodes": 3.0
            }
        },
        {
            "sequence": "[[0, 0, 0, 0, 0], [27, 0, 0, 37, 102], [10, 0, 0, 35, 159], [24, 1, 0, 194, 8], [40, 2, 0, 112, 106], [14, 3, 2, 72, 30], [25, 1, 4, 192, 97], [31, 2, 6, 112, 87], [6, 0, 2, 136, 112], [23, 3, 4, 193, 75], [0, 0, 5, 14, 103], [41, 5, 5, 146, 101], [1, 4, 1, 94, 178], [16, 1, 2, 152, 244], [20, 1, 7, 132, 130], [12, 5, 2, 113, 240], [9, 13, 4, 245, 208], [35, 12, 13, 58, 117], [40, 2, 3, 1, 50], [19, 11, 13, 167, 221], [34, 18, 10, 181, 183], [31, 2, 3, 88, 45], [31, 1, 21, 202, 48], [12, 21, 0, 99, 24], [19, 20, 11, 220, 83], [33, 1, 21, 172, 58], [4, 9, 18, 215, 198], [1, 16, 21, 147, 242], [33, 10, 15, 184, 167], [2, 16, 28, 63, 193], [27, 10, 19, 199, 36], [0, 19, 0, 0, 0]]",
            "fitness": {
                "fitness": 0.6850451542298683,
                "time": 0.01047048568725586,
                "act_nodes": 5.0
            }
        },
        {
            "sequence": "[[0, 0, 0, 0, 0], [3, 0, 0, 55, 102], [18, 0, 0, 35, 139], [24, 2, 0, 194, 173], [40, 2, 2, 112, 247], [9, 3, 2, 34, 30], [25, 5, 4, 43, 58], [36, 2, 6, 112, 87], [27, 7, 2, 136, 112], [23, 8, 3, 193, 185], [21, 0, 5, 14, 142], [36, 5, 4, 33, 148], [1, 11, 1, 249, 178], [16, 1, 4, 251, 244], [27, 1, 7, 17, 130], [12, 0, 8, 113, 240], [9, 1, 4, 216, 105], [35, 12, 16, 198, 74], [36, 2, 11, 1, 201], [19, 11, 17, 39, 178], [8, 15, 10, 181, 183], [31, 4, 3, 163, 45], [31, 1, 21, 151, 48], [11, 21, 22, 226, 115], [19, 10, 11, 213, 83], [1, 1, 21, 172, 201], [26, 18, 16, 130, 198], [30, 24, 21, 147, 149], [33, 6, 22, 184, 167], [2, 21, 28, 6, 199], [27, 10, 17, 39, 12], [0, 2, 0, 0, 0]]",
            "fitness": {
                "fitness": 0.8,
                "time": 0.0003075122833251953,
                "act_nodes": 1.0
            }
        },
        {
            "sequence": "[[0, 0, 0, 0, 0], [3, 0, 0, 37, 102], [10, 0, 0, 35, 159], [9, 2, 0, 194, 8], [40, 2, 0, 112, 167], [14, 3, 2, 34, 30], [25, 1, 4, 192, 58], [31, 2, 6, 73, 87], [28, 0, 2, 136, 112], [23, 3, 4, 193, 75], [31, 0, 5, 14, 103], [28, 5, 5, 146, 101], [1, 4, 1, 94, 178], [16, 1, 2, 152, 244], [20, 1, 7, 17, 130], [12, 5, 5, 254, 240], [3, 13, 4, 17, 208], [35, 12, 16, 198, 117], [36, 2, 8, 1, 50], [19, 11, 13, 166, 221], [34, 18, 10, 181, 183], [31, 3, 3, 88, 1], [31, 1, 21, 107, 156], [11, 21, 0, 4, 24], [19, 22, 11, 27, 83], [35, 1, 21, 172, 58], [4, 9, 18, 25, 198], [2, 24, 21, 147, 242], [25, 10, 25, 184, 167], [2, 14, 28, 63, 199], [27, 10, 19, 199, 36], [0, 15, 0, 0, 0]]",
            "fitness": {
                "fitness": 0.8,
                "time": 0.0009554862976074219,
                "act_nodes": 4.0
            }
        }
    ],
    "decoding": {
        "metadata": {
            "rows": 1,
            "columns": 30,
            "n_in": 1,
            "n_out": 1,
            "n_para": 2,
            "n_conn": 2
        },
        "functions": [
            "max",
            "min",
            "mean",
            "add",
            "subtract",
            "bitwise_not",
            "bitwise_or",
            "bitwise_and",
            "bitwise_and_mask",
            "bitwise_xor",
            "sqrt",
            "pow2",
            "exp",
            "log",
            "median_blur",
            "gaussian_blur",
            "laplacian",
            "sobel",
            "robert_cross",
            "canny",
            "sharpen",
            "gabor",
            "abs_diff",
            "abs_diff2",
            "fluo_tophat",
            "rel_diff",
            "erode",
            "dilate",
            "open",
            "close",
            "morph_gradient",
            "morph_tophat",
            "morph_blackhat",
            "fill_holes",
            "remove_small_objects",
            "remove_small_holes",
            "threshold",
            "threshold_at_1",
            "distance_transform",
            "distance_transform_and_thresh",
            "inrange_bin",
            "inrange"
        ],
        "endpoint": {
            "name": "Fit Ellipse",
            "abbv": "ELPS",
            "arity": 1,
            "args": 0,
            "kwargs": {
                "min_axis": 20,
                "max_axis": 60
            }
        },
        "mode": "default"
    }
}