{
    "dataset": {
        "name": "coins",
        "label_name": "coin",
        "indices": null
    },
    "population": [
        {
            "sequence": "[[0, 0, 0, 0, 0], [6, 0, 0, 229, 61], [22, 1, 0, 214, 68], [17, 0, 0, 219, 243], [3, 1, 1, 109, 105], [25, 0, 2, 110, 16], [3, 5, 2, 177, 27], [23, 2, 3, 251, 205], [20, 6, 6, 181, 238], [5, 2, 0, 45, 35], [41, 1, 4, 219, 180], [39, 0, 5, 141, 163], [41, 5, 5, 185, 164], [2, 2, 3, 237, 28], [10, 2, 2, 135, 165], [6, 7, 3, 156, 89], [25, 10, 11, 223, 221], [19, 14, 9, 248, 217], [30, 15, 16, 254, 97], [19, 18, 15, 48, 61], [23, 11, 12, 220, 170], [1, 6, 14, 47, 181], [6, 1, 8, 15, 119], [11, 12, 10, 158, 38], [9, 7, 20, 102, 151], [5, 11, 21, 59, 43], [15, 10, 1, 47, 68], [33, 0, 4, 113, 10], [18, 5, 27, 172, 162], [35, 10, 9, 37, 153], [7, 17, 9, 89, 75], [0, 30, 0, 0, 0]]",
            "fitness": {
                "fitness": 0.03708423728499808,
                "time": 0.00178375244140625,
                "act_nodes": 6.0
            }
        },
        {
            "sequence": "[[0, 0, 0, 0, 0], [6, 0, 0, 229, 61], [22, 1, 0, 214, 68], [17, 0, 0, 219, 243], [3, 1, 1, 109, 105], [25, 0, 2, 110, 16], [3, 5, 2, 177, 27], [23, 6, 5, 251, 205], [20, 6, 6, 181, 238], [5, 2, 0, 45, 35], [41, 1, 4, 219, 180], [39, 0, 5, 220, 163], [26, 5, 1, 185, 164], [2, 2, 3, 237, 28], [10, 2, 2, 135, 165], [6, 9, 3, 156, 255], [25, 10, 11, 223, 221], [19, 14, 9, 248, 31], [30, 17, 16, 254, 97], [19, 18, 16, 48, 61], [23, 17, 12, 143, 170], [1, 6, 14, 153, 181], [6, 1, 11, 15, 119], [11, 12, 10, 158, 38], [9, 14, 20, 102, 128], [5, 11, 11, 247, 43], [15, 8, 1, 47, 68], [33, 0, 4, 113, 10], [18, 25, 27, 172, 162], [35, 10, 9, 37, 153], [7, 23, 9, 89, 75], [0, 30, 0, 0, 0]]",
            "fitness": {
                "fitness": 0.8,
                "time": 0.0015906810760498047,
                "act_nodes": 7.0
            }
        },
        {
            "sequence": "[[0, 0, 0, 0, 0], [6, 0, 0, 229, 61], [31, 1, 0, 214, 68], [17, 0, 0, 164, 243], [20, 1, 3, 109, 191], [3, 2, 2, 110, 16], [3, 5, 2, 177, 27], [23, 2, 3, 251, 205], [20, 6, 6, 181, 238], [5, 8, 0, 45, 35], [1, 1, 0, 219, 180], [28, 7, 5, 141, 163], [41, 5, 5, 185, 164], [2, 2, 3, 237, 28], [10, 2, 2, 135, 165], [6, 7, 5, 156, 89], [25, 10, 11, 223, 96], [19, 14, 9, 248, 217], [30, 12, 16, 254, 97], [19, 18, 15, 48, 61], [23, 11, 12, 220, 170], [1, 3, 14, 47, 181], [6, 15, 8, 15, 119], [11, 12, 10, 158, 38], [9, 7, 20, 102, 151], [5, 11, 21, 59, 43], [15, 10, 1, 47, 68], [33, 0, 4, 113, 10], [18, 5, 6, 172, 162], [37, 25, 9, 37, 153], [7, 17, 9, 0, 75], [0, 2, 0, 0, 0]]",
            "fitness": {
                "fitness": 0.8,
                "time": 0.0012225627899169922,
                "act_nodes": 2.0
            }
        },
        {
            "sequence": "[[0, 0, 0, 0, 0], [32, 0, 0, 229, 252], [22, 1, 0, 214, 71], [17, 0, 0, 219, 243], [3, 1, 2, 109, 105], [25, 0, 2, 110, 16], [3, 4, 4, 177, 27], [7, 2, 3, 251, 205], [20, 6, 4, 171, 238], [38, 2, 0, 45, 35], [41, 1, 6, 219, 211], [39, 0, 5, 141, 227], [41, 5, 5, 243, 230], [2, 2, 7, 237, 28], [20, 8, 2, 106, 157], [6, 8, 7, 156, 89], [25, 10, 11, 223, 203], [15, 14, 9, 20, 217], [29, 15, 3, 254, 97], [22, 18, 15, 171, 249], [37, 11, 12, 177, 186], [1, 0, 9, 47, 206], [6, 1, 8, 15, 105], [6, 12, 19, 158, 38], [9, 7, 5, 67, 151], [35, 12, 21, 59, 128], [15, 10, 1, 47, 68], [10, 0, 4, 113, 10], [22, 5, 0, 172, 162], [35, 19, 25, 37, 56], [7, 17, 9, 143, 214], [0, 30, 0, 0, 0]]",
            "fitness": {
                "fitness": 0.8,
                "time": 0.0017145633697509765,
                "act_nodes": 9.0
            }
        },
        {
            "sequence": "[[0, 0, 0, 0, 0], [6, 0, 0, 229, 61], [35, 1, 0, 214, 68], [18, 0, 0, 137, 243], [3, 1, 1, 109, 101], [25, 1, 1, 214, 16], [36, 5, 2, 177, 222], [23, 5, 3, 251, 205], [20, 1, 1, 181, 238], [5, 1, 0, 45, 35], [41, 7, 4, 219, 180], [12, 0, 5, 141, 163], [41, 5, 5, 185, 227], [20, 2, 5, 237, 28], [10, 2, 1, 135, 165], [6, 10, 3, 156, 249], [25, 3, 11, 223, 221], [2, 14, 9, 248, 217], [9, 15, 16, 118, 97], [7, 18, 15, 20, 61], [23, 15, 12, 220, 136], [41, 6, 14, 47, 181], [28, 1, 14, 179, 62], [11, 9, 12, 82, 38], [9, 7, 20, 102, 108], [2, 11, 5, 81, 223], [15, 11, 1, 47, 102], [33, 0, 4, 158, 10], [18, 18, 27, 172, 155], [12, 10, 9, 37, 80], [7, 21, 9, 89, 75], [0, 30, 0, 0, 0]]",
            "fitness": {
                "fitness": 0.8,
                "time": 0.0012349605560302735,
                "act_nodes": 6.0
            }
        },
        {
            "sequence": "[[0, 0, 0, 0, 0], [29, 0, 0, 229, 61], [22, 1, 0, 214, 68], [39, 0, 2, 219, 201], [3, 0, 1, 101, 105], [25, 0, 2, 110, 108], [3, 5, 2, 177, 27], [23, 2, 3, 251, 205], [20, 6, 6, 181, 238], [5, 2, 0, 45, 35], [41, 1, 4, 219, 180], [39, 0, 5, 141, 163], [28, 5, 5, 185, 164], [2, 5, 3, 237, 28], [10, 2, 2, 135, 165], [6, 7, 3, 156, 89], [25, 10, 11, 68, 221], [19, 4, 9, 158, 217], [30, 15, 16, 121, 97], [19, 18, 15, 48, 20], [23, 11, 12, 220, 170], [1, 6, 0, 47, 181], [6, 1, 8, 15, 119], [11, 10, 10, 158, 38], [9, 2, 20, 102, 151], [5, 11, 21, 59, 43], [15, 10, 19, 47, 68], [33, 0, 4, 113, 10], [18, 5, 27, 229, 162], [35, 10, 8, 59, 153], [7, 17, 9, 118, 75], [0, 30, 0, 0, 0]]",
            "fitness": {
                "fitness": 0.5742914334647727,
                "time": 0.0028363704681396485,
                "act_nodes": 6.0
            }
        }
    ],
    "decoding": {
        "metadata": {
            "rows": 1,
            "columns": 30,
            "n_in": 1,
            "n_out": 1,
            "n_para": 2,
            "n_conn": 2
        },
        "functions": [
            "max",
            "min",
            "mean",
            "add",
            "subtract",
            "bitwise_not",
            "bitwise_or",
            "bitwise_and",
            "bitwise_and_mask",
            "bitwise_xor",
            "sqrt",
            "pow2",
            "exp",
            "log",
            "median_blur",
            "gaussian_blur",
            "laplacian",
            "sobel",
            "robert_cross",
            "canny",
            "sharpen",
            "gabor",
            "abs_diff",
            "abs_diff2",
            "fluo_tophat",
            "rel_diff",
            "erode",
            "dilate",
            "open",
            "close",
            "morph_gradient",
            "morph_tophat",
            "morph_blackhat",
            "fill_holes",
            "remove_small_objects",
            "remove_small_holes",
            "threshold",
            "threshold_at_1",
            "distance_transform",
            "distance_transform_and_thresh",
            "inrange_bin",
            "inrange"
        ],
        "endpoint": {
            "name": "Fit Ellipse",
            "abbv": "ELPS",
            "arity": 1,
            "args": 0,
            "kwargs": {
                "min_axis": 20,
                "max_axis": 60
            }
        },
        "mode": "default"
    }
}